{
  "info": {
    "description": "ISAT",
    "folder": "C:/Users/CHUJIAO/Desktop/膝关节超声/数据/膝关节2025/痛风性关节炎/902212293_彭俊龙",
    "name": "彭俊龙_69591227.jpg",
    "width": 1280,
    "height": 960,
    "depth": 3,
    "note": ""
  },
  "objects": [
    {
      "category": "GA痛风石",
      "group": 1,
      "segmentation": [
        [
          270.72,
          240.49
        ],
        [
          496.76,
          202.38
        ],
        [
          787.19,
          210.27
        ],
        [
          986.94,
          233.92
        ],
        [
          1001.4,
          425.79
        ],
        [
          893.63,
          348.25
        ],
        [
          827.93,
          303.57
        ],
        [
          697.82,
          306.2
        ],
        [
          622.92,
          300.94
        ],
        [
          548.01,
          321.97
        ],
        [
          358.77,
          356.14
        ],
        [
          311.46,
          318.03
        ],
        [
          266.78,
          289.12
        ]
      ],
      "area": 82380.60117468977,
      "layer": 1.0,
      "bbox": [
        266.08476998049724,
        201.8821143544109,
        1001.8948907929323,
        426.19641544385
      ],
      "iscrowd": false,
      "note": ""
    }
  ]
}