{
  "info": {
    "description": "ISAT",
    "folder": "C:/Users/CHUJIAO/Desktop/膝关节超声/数据/膝关节2025/骨性关节炎/901565621_张雅秋",
    "name": "张雅秋_63062759.jpg",
    "width": 1280,
    "height": 960,
    "depth": 3,
    "note": ""
  },
  "objects": [
    {
      "category": "OA骨皮质",
      "group": 1,
      "segmentation": [
        [
          389.0,
          356.0
        ],
        [
          352.0,
          357.0
        ],
        [
          345.0,
          358.0
        ],
        [
          342.0,
          361.0
        ],
        [
          339.0,
          362.0
        ],
        [
          342.0,
          365.0
        ],
        [
          348.0,
          366.0
        ],
        [
          355.0,
          367.0
        ],
        [
          361.0,
          366.0
        ],
        [
          364.0,
          366.0
        ],
        [
          373.0,
          367.0
        ],
        [
          382.0,
          365.0
        ],
        [
          387.0,
          365.0
        ],
        [
          395.0,
          365.0
        ],
        [
          398.0,
          365.0
        ],
        [
          410.0,
          367.0
        ],
        [
          422.0,
          367.0
        ],
        [
          427.0,
          369.0
        ],
        [
          436.0,
          370.0
        ],
        [
          449.0,
          370.0
        ],
        [
          452.0,
          368.0
        ],
        [
          459.0,
          369.0
        ],
        [
          462.0,
          367.0
        ],
        [
          466.0,
          369.0
        ],
        [
          475.0,
          370.0
        ],
        [
          483.0,
          370.0
        ],
        [
          488.0,
          371.0
        ],
        [
          490.0,
          372.0
        ],
        [
          494.0,
          376.0
        ],
        [
          496.0,
          377.0
        ],
        [
          505.0,
          380.0
        ],
        [
          509.0,
          381.0
        ],
        [
          523.0,
          381.0
        ],
        [
          530.0,
          382.0
        ],
        [
          534.0,
          383.0
        ],
        [
          537.0,
          385.0
        ],
        [
          541.0,
          386.0
        ],
        [
          545.0,
          387.0
        ],
        [
          550.0,
          388.0
        ],
        [
          558.0,
          388.0
        ],
        [
          565.0,
          389.0
        ],
        [
          568.0,
          390.0
        ],
        [
          573.0,
          393.0
        ],
        [
          576.0,
          393.0
        ],
        [
          584.0,
          397.0
        ],
        [
          590.0,
          402.0
        ],
        [
          592.0,
          403.0
        ],
        [
          603.0,
          404.0
        ],
        [
          619.0,
          404.0
        ],
        [
          627.0,
          406.0
        ],
        [
          637.0,
          406.0
        ],
        [
          642.0,
          404.0
        ],
        [
          657.0,
          404.0
        ],
        [
          660.0,
          403.0
        ],
        [
          663.0,
          401.0
        ],
        [
          666.0,
          401.0
        ],
        [
          673.0,
          397.0
        ],
        [
          678.0,
          396.0
        ],
        [
          711.0,
          396.0
        ],
        [
          728.0,
          397.0
        ],
        [
          736.0,
          399.0
        ],
        [
          747.0,
          399.0
        ],
        [
          750.0,
          400.0
        ],
        [
          753.0,
          401.0
        ],
        [
          755.0,
          402.0
        ],
        [
          759.0,
          405.0
        ],
        [
          761.0,
          406.0
        ],
        [
          765.0,
          407.0
        ],
        [
          767.0,
          408.0
        ],
        [
          772.0,
          414.0
        ],
        [
          775.0,
          416.0
        ],
        [
          780.0,
          419.0
        ],
        [
          782.0,
          419.0
        ],
        [
          785.0,
          421.0
        ],
        [
          788.0,
          423.0
        ],
        [
          791.0,
          426.0
        ],
        [
          796.0,
          432.0
        ],
        [
          799.0,
          433.0
        ],
        [
          802.0,
          436.0
        ],
        [
          808.0,
          439.0
        ],
        [
          820.0,
          450.0
        ],
        [
          822.0,
          452.0
        ],
        [
          829.0,
          460.0
        ],
        [
          830.0,
          462.0
        ],
        [
          831.0,
          467.0
        ],
        [
          832.0,
          469.0
        ],
        [
          837.0,
          474.0
        ],
        [
          840.0,
          475.0
        ],
        [
          843.0,
          477.0
        ],
        [
          847.0,
          476.0
        ],
        [
          849.0,
          475.0
        ],
        [
          853.0,
          470.0
        ],
        [
          852.0,
          462.0
        ],
        [
          850.0,
          459.0
        ],
        [
          850.0,
          457.0
        ],
        [
          849.0,
          455.0
        ],
        [
          847.0,
          453.0
        ],
        [
          842.0,
          451.0
        ],
        [
          838.0,
          447.0
        ],
        [
          838.0,
          444.0
        ],
        [
          837.0,
          442.0
        ],
        [
          835.0,
          440.0
        ],
        [
          835.0,
          438.0
        ],
        [
          830.0,
          434.0
        ],
        [
          829.0,
          433.0
        ],
        [
          828.0,
          430.0
        ],
        [
          823.0,
          424.0
        ],
        [
          807.0,
          409.0
        ],
        [
          803.0,
          406.0
        ],
        [
          796.0,
          402.0
        ],
        [
          792.0,
          397.0
        ],
        [
          790.0,
          395.0
        ],
        [
          789.0,
          395.0
        ],
        [
          786.0,
          392.0
        ],
        [
          784.0,
          391.0
        ],
        [
          782.0,
          390.0
        ],
        [
          773.0,
          387.0
        ],
        [
          764.0,
          386.0
        ],
        [
          755.0,
          383.0
        ],
        [
          750.0,
          382.0
        ],
        [
          742.0,
          381.0
        ],
        [
          740.0,
          381.0
        ],
        [
          736.0,
          382.0
        ],
        [
          728.0,
          382.0
        ],
        [
          726.0,
          382.0
        ],
        [
          708.0,
          381.0
        ],
        [
          697.0,
          383.0
        ],
        [
          683.0,
          383.0
        ],
        [
          675.0,
          384.0
        ],
        [
          668.0,
          386.0
        ],
        [
          661.0,
          387.0
        ],
        [
          651.0,
          388.0
        ],
        [
          632.0,
          390.0
        ],
        [
          622.0,
          390.0
        ],
        [
          617.0,
          389.0
        ],
        [
          612.0,
          388.0
        ],
        [
          608.0,
          387.0
        ],
        [
          604.0,
          386.0
        ],
        [
          597.0,
          382.0
        ],
        [
          592.0,
          380.0
        ],
        [
          587.0,
          379.0
        ],
        [
          582.0,
          379.0
        ],
        [
          577.0,
          377.0
        ],
        [
          571.0,
          376.0
        ],
        [
          564.0,
          376.0
        ],
        [
          559.0,
          375.0
        ],
        [
          555.0,
          374.0
        ],
        [
          547.0,
          371.0
        ],
        [
          543.0,
          371.0
        ],
        [
          540.0,
          369.0
        ],
        [
          537.0,
          368.0
        ],
        [
          528.0,
          366.0
        ],
        [
          518.0,
          365.0
        ],
        [
          514.0,
          364.0
        ],
        [
          507.0,
          361.0
        ],
        [
          502.0,
          361.0
        ],
        [
          496.0,
          358.0
        ],
        [
          490.0,
          357.0
        ],
        [
          477.0,
          356.0
        ],
        [
          451.0,
          358.0
        ],
        [
          422.0,
          358.0
        ],
        [
          417.0,
          356.0
        ]
      ],
      "area": 8467.5,
      "layer": 1.0,
      "bbox": [
        338.6464466094067,
        355.35006631638026,
        853.4961389383568,
        477.4850712500727
      ],
      "iscrowd": false,
      "note": ""
    },
    {
      "category": "OA骨皮质",
      "group": 2,
      "segmentation": [
        [
          988.0,
          344.0
        ],
        [
          973.0,
          345.0
        ],
        [
          963.0,
          346.0
        ],
        [
          957.0,
          347.0
        ],
        [
          951.0,
          349.0
        ],
        [
          939.0,
          350.0
        ],
        [
          935.0,
          351.0
        ],
        [
          923.0,
          356.0
        ],
        [
          919.0,
          356.0
        ],
        [
          909.0,
          354.0
        ],
        [
          900.0,
          354.0
        ],
        [
          898.0,
          355.0
        ],
        [
          897.0,
          356.0
        ],
        [
          896.0,
          358.0
        ],
        [
          897.0,
          361.0
        ],
        [
          901.0,
          369.0
        ],
        [
          904.0,
          372.0
        ],
        [
          905.0,
          372.0
        ],
        [
          907.0,
          375.0
        ],
        [
          910.0,
          376.0
        ],
        [
          918.0,
          378.0
        ],
        [
          921.0,
          380.0
        ],
        [
          923.0,
          380.0
        ],
        [
          926.0,
          379.0
        ],
        [
          931.0,
          375.0
        ],
        [
          933.0,
          374.0
        ],
        [
          935.0,
          374.0
        ],
        [
          937.0,
          373.0
        ],
        [
          939.0,
          372.0
        ],
        [
          943.0,
          368.0
        ],
        [
          947.0,
          368.0
        ],
        [
          950.0,
          366.0
        ],
        [
          957.0,
          365.0
        ],
        [
          958.0,
          367.0
        ],
        [
          959.0,
          368.0
        ],
        [
          961.0,
          369.0
        ],
        [
          963.0,
          369.0
        ],
        [
          968.0,
          368.0
        ],
        [
          974.0,
          365.0
        ],
        [
          977.0,
          364.0
        ],
        [
          981.0,
          363.0
        ],
        [
          1006.0,
          363.0
        ],
        [
          1011.0,
          364.0
        ],
        [
          1016.0,
          365.0
        ],
        [
          1025.0,
          368.0
        ],
        [
          1042.0,
          371.0
        ],
        [
          1060.0,
          372.0
        ],
        [
          1079.0,
          373.0
        ],
        [
          1079.0,
          376.0
        ],
        [
          1082.0,
          380.0
        ],
        [
          1082.0,
          370.0
        ],
        [
          1083.0,
          369.0
        ],
        [
          1083.0,
          354.0
        ],
        [
          1082.0,
          353.0
        ],
        [
          1082.0,
          347.0
        ],
        [
          1080.0,
          346.0
        ],
        [
          1072.0,
          347.0
        ],
        [
          1041.0,
          346.0
        ],
        [
          1010.0,
          344.0
        ]
      ],
      "area": 4042.0,
      "layer": 2.0,
      "bbox": [
        895.5256583509747,
        343.4678479158098,
        1083.5,
        380.5
      ],
      "iscrowd": false,
      "note": ""
    },
    {
      "category": "OA内侧半月板",
      "group": 3,
      "segmentation": [
        [
          783.24,
          378.48
        ],
        [
          826.61,
          335.11
        ],
        [
          871.29,
          331.17
        ],
        [
          893.63,
          356.14
        ],
        [
          891.01,
          490.18
        ]
      ],
      "area": 9880.387403075438,
      "layer": 3.0,
      "bbox": [
        782.5372464015651,
        330.6723662864863,
        894.1344008307462,
        490.69451087642693
      ],
      "iscrowd": 0,
      "note": ""
    }
  ]
}